<?xml version="1.0" encoding="UTF-8"?>
<root>
  <row>
    <potus gender="male">George Washington</potus>
    <party> </party>
    <start>1789</start>
    <end>1797</end>
    <vpotus gender="male">John Adams</vpotus>
  </row>
  <row>
    <potus gender="male">John Adams</potus>
    <party>Federalist</party>
    <start>1797</start>
    <end>1801</end>
    <vpotus gender="male">Thomas Jefferson</vpotus>
  </row>
  <row>
    <potus gender="male">Thomas Jefferson</potus>
    <party>Democratic-Republican</party>
    <start>1801</start>
    <end>1805</end>
    <vpotus gender="male">Aaron Burr</vpotus>
  </row>
  <row>
    <potus gender="male">Thomas Jefferson</potus>
    <party>Democratic-Republican</party>
    <start>1805</start>
    <end>1809</end>
    <vpotus gender="male">George Clinton</vpotus>
  </row>
  <row>
    <potus gender="male">James Madison</potus>
    <party>Democratic-Republican</party>
    <start>1809</start>
    <end>1812</end>
    <vpotus gender="male">George Clinton</vpotus>
  </row>
  <row>
    <potus gender="male">James Madison</potus>
    <party>Democratic-Republican</party>
    <start>1812</start>
    <end>1813</end>
    <vpotus gender=""> </vpotus>
  </row>
  <row>
    <potus gender="male">James Madison</potus>
    <party>Democratic-Republican</party>
    <start>1813</start>
    <end>1814</end>
    <vpotus gender="male">Elbridge Gerry</vpotus>
  </row>
  <row>
    <potus gender="male">James Madison</potus>
    <party>Democratic-Republican</party>
    <start>1814</start>
    <end>1817</end>
    <vpotus gender=""> </vpotus>
  </row>
  <row>
    <potus gender="male">James Monroe</potus>
    <party>Democratic-Republican</party>
    <start>1817</start>
    <end>1825</end>
    <vpotus gender="male">Daniel D. Tompkins</vpotus>
  </row>
  <row>
    <potus gender="male">John Quincy Adams</potus>
    <party>Democratic-Republican</party>
    <start>1825</start>
    <end>1829</end>
    <vpotus gender="male">John C. Calhoun</vpotus>
  </row>
  <row>
    <potus gender="male">Andrew Jackson</potus>
    <party>Democratic</party>
    <start>1829</start>
    <end>1832</end>
    <vpotus gender="male">John C. Calhoun</vpotus>
  </row>
  <row>
    <potus gender="male">Andrew Jackson</potus>
    <party>Democratic</party>
    <start>1832</start>
    <end>1833</end>
    <vpotus gender=""> </vpotus>
  </row>
  <row>
    <potus gender="male">Andrew Jackson</potus>
    <party>Democratic</party>
    <start>1833</start>
    <end>1837</end>
    <vpotus gender="male">Martin Van Buren</vpotus>
  </row>
  <row>
    <potus gender="male">Martin Van Buren</potus>
    <party>Democratic</party>
    <start>1837</start>
    <end>1841</end>
    <vpotus gender="male">Richard M. Johnson</vpotus>
  </row>
  <row>
    <potus gender="male">William Henry Harrison</potus>
    <party>Whig</party>
    <start>1841</start>
    <end>1841</end>
    <vpotus gender="male">John Tyler</vpotus>
  </row>
  <row>
    <potus gender="male">John Tyler</potus>
    <party>Whig</party>
    <start>1841</start>
    <end>1845</end>
    <vpotus gender="">No Vice President</vpotus>
  </row>
  <row>
    <potus gender="male">James Knox Polk</potus>
    <party>Democratic</party>
    <start>1845</start>
    <end>1849</end>
    <vpotus gender="male">George M. Dallas</vpotus>
  </row>
  <row>
    <potus gender="male">Zachary Taylor</potus>
    <party>Whig</party>
    <start>1849</start>
    <end>1850</end>
    <vpotus gender="male">Millard Fillmore</vpotus>
  </row>
  <row>
    <potus gender="male">Millard Fillmore</potus>
    <party>Whig</party>
    <start>1850</start>
    <end>1853</end>
    <vpotus gender="male"> </vpotus>
  </row>
  <row>
    <potus gender="male">Franklin Pierce</potus>
    <party>Democratic</party>
    <start>1853</start>
    <end>1853</end>
    <vpotus gender="male">William R. King</vpotus>
  </row>
  <row>
    <potus gender="male">Franklin Pierce</potus>
    <party>Democratic</party>
    <start>1853</start>
    <end>1857</end>
    <vpotus gender=""> </vpotus>
  </row>
  <row>
    <potus gender="male">James Buchanan</potus>
    <party>Democratic</party>
    <start>1857</start>
    <end>1861</end>
    <vpotus gender="male">John C. Breckinridge</vpotus>
  </row>
  <row>
    <potus gender="male">Abraham Lincoln</potus>
    <party>Republican</party>
    <start>1861</start>
    <end>1865</end>
    <vpotus gender="male">Hannibal Hamlin</vpotus>
  </row>
  <row>
    <potus gender="male">Abraham Lincoln</potus>
    <party>Republican</party>
    <start>1861</start>
    <end>1865</end>
    <vpotus gender="male">Andrew Johnson</vpotus>
  </row>
  <row>
    <potus gender="male">Andrew Johnson</potus>
    <party>Democratic/National Union</party>
    <start>1865</start>
    <end>1869</end>
    <vpotus gender="male"> </vpotus>
  </row>
  <row>
    <potus gender="male">Ulysses Simpson Grant</potus>
    <party>Republican</party>
    <start>1869</start>
    <end>1873</end>
    <vpotus gender="male">Schuyler Colfax</vpotus>
  </row>
  <row>
    <potus gender="male">Ulysses Simpson Grant</potus>
    <party>Republican</party>
    <start>1873</start>
    <end>1875</end>
    <vpotus gender="male">Henry Wilson</vpotus>
  </row>
  <row>
    <potus gender="male">Ulysses Simpson Grant</potus>
    <party>Republican</party>
    <start>1875</start>
    <end>1877</end>
    <vpotus gender="male"> </vpotus>
  </row>
  <row>
    <potus gender="male">Rutherford Birchard Hayes</potus>
    <party>Republican</party>
    <start>1877</start>
    <end>1881</end>
    <vpotus gender="male">William A. Wheeler</vpotus>
  </row>
  <row>
    <potus gender="male">James Abram Garfield</potus>
    <party>Republican</party>
    <start>1881</start>
    <end>1881</end>
    <vpotus>Chester A. Arthur</vpotus>
  </row>
  <row>
    <potus gender="male">Chester Alan Arthur</potus>
    <party>Republican</party>
    <start>1881</start>
    <end>1885</end>
    <vpotus gender=""> </vpotus>
  </row>
  <row>
    <potus gender="male">Grover Cleveland</potus>
    <party>Democratic</party>
    <start>1885</start>
    <end>1885</end>
    <vpotus gender="male">Thomas A. Hendricks</vpotus>
  </row>
  <row>
    <potus gender="male">Grover Cleveland</potus>
    <party>Democratic</party>
    <start>1885</start>
    <end>1889</end>
    <vpotus gender=""> </vpotus>
  </row>
  <row>
    <potus gender="male">Benjamin Harrison</potus>
    <party>Republican</party>
    <start>1889</start>
    <end>1893</end>
    <vpotus gender="male">Levi P. Morton</vpotus>
  </row>
  <row>
    <potus gender="male">Grover Cleveland</potus>
    <party>Democratic</party>
    <start>1893</start>
    <end>1897</end>
    <vpotus gender="male">Adlai E. Stevenson</vpotus>
  </row>
  <row>
    <potus gender="male">William McKinley</potus>
    <party>Republican</party>
    <start>1897</start>
    <end>1899</end>
    <vpotus gender="male">Garret A. Hobart</vpotus>
  </row>
  <row>
    <potus gender="male">William McKinley</potus>
    <party>Republican</party>
    <start>1899</start>
    <end>1901</end>
    <vpotus gender="male">No VP</vpotus>
  </row>
  <row>
    <potus gender="male">William McKinley</potus>
    <party>Republican</party>
    <start>1901</start>
    <end>1901</end>
    <vpotus gender="male">Theodore Roosevelt</vpotus>
  </row>
  <row>
    <potus gender="male">Theodore Roosevelt</potus>
    <party>Republican</party>
    <start>1901</start>
    <end>1905</end>
    <vpotus gender="male"> </vpotus>
  </row>
  <row>
    <potus gender="male">Theodore Roosevelt</potus>
    <party>Republican</party>
    <start>1905</start>
    <end>1909</end>
    <vpotus gender="male">Charles W. Fairbanks</vpotus>
  </row>
  <row>
    <potus gender="male">William Howard Taft</potus>
    <party>Republican</party>
    <start>1909</start>
    <end>1912</end>
    <vpotus gender="male">James S. Sherman</vpotus>
  </row>
  <row>
    <potus gender="male">William Howard Taft</potus>
    <party>Republican</party>
    <start>1912</start>
    <end>1913</end>
    <vpotus gender="male"> </vpotus>
  </row>
  <row>
    <potus gender="male">Woodrow Wilson</potus>
    <party>Democratic</party>
    <start>1913</start>
    <end>1921</end>
    <vpotus gender="male">Thomas R. Marshall</vpotus>
  </row>
  <row>
    <potus gender="male">Warren Gamaliel Harding</potus>
    <party>Republican</party>
    <start>1921</start>
    <end>1923</end>
    <vpotus gender="male">Calvin Coolidge</vpotus>
  </row>
  <row>
    <potus gender="male">Calvin Coolidge</potus>
    <party>Republican</party>
    <start>1923</start>
    <end>1925</end>
    <vpotus gender="male"> </vpotus>
  </row>
  <row>
    <potus gender="male">Calvin Coolidge</potus>
    <party>Republican</party>
    <start>1925</start>
    <end>1929</end>
    <vpotus gender="male">Charles G. Dawes</vpotus>
  </row>
  <row>
    <potus gender="male">Herbert Clark Hoover</potus>
    <party>Republican</party>
    <start>1929</start>
    <end>1933</end>
    <vpotus gender="male">Charles Curtis</vpotus>
  </row>
  <row>
    <potus gender="male">Franklin Delano Roosevelt</potus>
    <party>Democratic</party>
    <start>1933</start>
    <end>1941</end>
    <vpotus gender="male">John N. Garner</vpotus>
  </row>
  <row>
    <potus gender="male">Franklin Delano Roosevelt</potus>
    <party>Democratic</party>
    <start>1941</start>
    <end>1945</end>
    <vpotus gender="male">Henry A. Wallace</vpotus>
  </row>
  <row>
    <potus gender="male">Franklin Delano Roosevelt</potus>
    <party>Democratic</party>
    <start>1945</start>
    <end>1945</end>
    <vpotus gender="male">Harry S. Truman</vpotus>
  </row>
  <row>
    <potus gender="male">Harry S. Truman</potus>
    <party>Democratic</party>
    <start>1945</start>
    <end>1949</end>
    <vpotus gender="male"> </vpotus>
  </row>
  <row>
    <potus gender="male">Harry S. Truman</potus>
    <party>Democratic</party>
    <start>1945</start>
    <end>1953</end>
    <vpotus gender="male">Alben W. Barkley</vpotus>
  </row>
  <row>
    <potus gender="male">Dwight David Eisenhower</potus>
    <party>Republican</party>
    <start>1953</start>
    <end>1961</end>
    <vpotus gender="male">Richard M. Nixon</vpotus>
  </row>
  <row>
    <potus gender="male">John Fitzgerald Kennedy</potus>
    <party>Democratic</party>
    <start>1961</start>
    <end>1963</end>
    <vpotus gender="male">Lyndon B. Johnson</vpotus>
  </row>
  <row>
    <potus gender="male">Lyndon Baines Johnson</potus>
    <party>Democratic</party>
    <start>1963</start>
    <end>1969</end>
    <vpotus gender="male"> </vpotus>
  </row>
  <row>
    <potus gender="male">Lyndon Baines Johnson</potus>
    <party>Democratic</party>
    <start>1963</start>
    <end>1969</end>
    <vpotus gender="male">Hubert H. Humphrey</vpotus>
  </row>
  <row>
    <potus gender="male">Richard Milhous Nixon</potus>
    <party>Republican</party>
    <start>1969</start>
    <end>1973</end>
    <vpotus gender="male">Spiro T. Agnew</vpotus>
  </row>
  <row>
    <potus gender="male">Richard Milhous Nixon</potus>
    <party>Republican</party>
    <start>1973</start>
    <end>1973</end>
    <vpotus gender="male"> </vpotus>
  </row>
  <row>
    <potus gender="male">Richard Milhous Nixon</potus>
    <party>Republican</party>
    <start>1973</start>
    <end>1974</end>
    <vpotus gender="male">Gerald R. Ford</vpotus>
  </row>
  <row>
    <potus gender="male">Gerald Rudolph Ford</potus>
    <party>Republican</party>
    <start>1974</start>
    <end>1974</end>
    <vpotus gender="male"> </vpotus>
  </row>
  <row>
    <potus gender="male">Gerald Rudolph Ford</potus>
    <party>Republican</party>
    <start>1974</start>
    <end>1977</end>
    <vpotus gender="male">Nelson A. Rockefeller</vpotus>
  </row>
  <row>
    <potus gender="male">Jimmy Carter</potus>
    <party>Democratic</party>
    <start>1977</start>
    <end>1981</end>
    <vpotus gender="male">Walter F. Mondale</vpotus>
  </row>
  <row>
    <potus gender="male">Ronald Wilson Reagan</potus>
    <party>Republican</party>
    <start>1981</start>
    <end>1989</end>
    <vpotus gender="male">George H. W. Bush</vpotus>
  </row>
  <row>
    <potus gender="male">George Herbert Walker Bush</potus>
    <party>Republican</party>
    <start>1989</start>
    <end>1993</end>
    <vpotus gender="male">J. Danforth Quayle</vpotus>
  </row>
  <row>
    <potus gender="male">Bill Clinton</potus>
    <party>Democratic</party>
    <start>1993</start>
    <end>2001</end>
    <vpotus gender="male">Albert Gore, Jr.</vpotus>
  </row>
  <row>
    <potus gender="male">George Walker Bush</potus>
    <party>Republican</party>
    <start>2001</start>
    <end>2009</end>
    <vpotus gender="male">Dick Cheney</vpotus>
  </row>
  <row>
    <potus gender="male">Barack Obama</potus>
    <party>Democratic</party>
    <start>2009</start>
    <end>2017</end>
    <vpotus gender="male">Joseph Biden</vpotus>
  </row>
  <row>
    <potus gender="male">Donald John Trump</potus>
    <party>Republican</party>
    <start>2017</start>
    <end>2021</end>
    <vpotus gender="male">Mike Pence</vpotus>
  </row>
  <row>
    <potus gender="male">Joseph Biden</potus>
    <party>Democratic</party>
    <start>2021</start>
    <end>2025</end>
    <vpotus gender="male">Kamala Harris</vpotus>
  </row>
  <row>
    <potus gender="female">Kamala Harris</potus>
    <party>Democratic</party>
    <start>2025</start>
    <end>2033</end>
    <vpotus gender="male">Tim Walz</vpotus>
  </row>
</root>